fofa/__init__.py
fofa/__main__.py
fofa/client.py
fofa/exception.py
fofa/helper.py
FOFA_py-2.0.3.dist-info/LICENSE
FOFA_py-2.0.3.dist-info/METADATA
FOFA_py-2.0.3.dist-info/WHEEL
FOFA_py-2.0.3.dist-info/entry_points.txt
FOFA_py-2.0.3.dist-info/top_level.txt
FOFA_py-2.0.3.dist-info/RECORD
