Metadata-Version: 2.1
Name: FOFA-py
Version: 2.0.3
Summary: Python library for FOFA (https://fofa.info)
Home-page: https://github.com/fofapro/fofa-py
Author: Fofa
Author-email: fofabot@baimaohui.net
License: MIT
Keywords: fofa,security,network
Platform: UNKNOWN
Classifier: Intended Audience :: Developers
Classifier: License :: OSI Approved :: MIT License
Classifier: Operating System :: OS Independent
Classifier: Programming Language :: Python :: 3
Classifier: Programming Language :: Python :: 3.7
Classifier: Programming Language :: Python :: 3.8
Classifier: Programming Language :: Python :: 3.9
Classifier: Programming Language :: Python :: 3.10
Classifier: Programming Language :: Python :: 3.11
Classifier: Topic :: Software Development :: Libraries :: Python Modules
Requires-Dist: click
Requires-Dist: requests (>=2.2.1)
Requires-Dist: retry
Requires-Dist: XlsxWriter
Requires-Dist: tqdm
Requires-Dist: tabulate
